colors/__init__.py
colors/colors.py
pycolorslib-0.1.2.dist-info/licenses/LICENSE
pycolorslib-0.1.2.dist-info/METADATA
pycolorslib-0.1.2.dist-info/WHEEL
pycolorslib-0.1.2.dist-info/top_level.txt
pycolorslib-0.1.2.dist-info/RECORD
