Metadata-Version: 2.4
Name: pycolorslib
Version: 0.1.2
Summary: A library that adds colour variables
Author: kovu
License: MIT
Requires-Python: >=3.8
License-File: LICENSE
Dynamic: license-file
